doctr/__init__.py
doctr/file_utils.py
doctr/py.typed
doctr/version.py
doctr/contrib/__init__.py
doctr/contrib/artefacts.py
doctr/contrib/base.py
doctr/datasets/__init__.py
doctr/datasets/coco_text.py
doctr/datasets/cord.py
doctr/datasets/detection.py
doctr/datasets/doc_artefacts.py
doctr/datasets/funsd.py
doctr/datasets/ic03.py
doctr/datasets/ic13.py
doctr/datasets/iiit5k.py
doctr/datasets/iiithws.py
doctr/datasets/imgur5k.py
doctr/datasets/mjsynth.py
doctr/datasets/ocr.py
doctr/datasets/orientation.py
doctr/datasets/recognition.py
doctr/datasets/sroie.py
doctr/datasets/svhn.py
doctr/datasets/svt.py
doctr/datasets/synthtext.py
doctr/datasets/utils.py
doctr/datasets/vocabs.py
doctr/datasets/wildreceipt.py
doctr/datasets/datasets/__init__.py
doctr/datasets/datasets/base.py
doctr/datasets/datasets/pytorch.py
doctr/datasets/generator/__init__.py
doctr/datasets/generator/base.py
doctr/datasets/generator/pytorch.py
doctr/io/__init__.py
doctr/io/elements.py
doctr/io/html.py
doctr/io/pdf.py
doctr/io/reader.py
doctr/io/image/__init__.py
doctr/io/image/base.py
doctr/io/image/pytorch.py
doctr/models/__init__.py
doctr/models/_utils.py
doctr/models/builder.py
doctr/models/core.py
doctr/models/zoo.py
doctr/models/classification/__init__.py
doctr/models/classification/zoo.py
doctr/models/classification/magc_resnet/__init__.py
doctr/models/classification/magc_resnet/pytorch.py
doctr/models/classification/mobilenet/__init__.py
doctr/models/classification/mobilenet/pytorch.py
doctr/models/classification/predictor/__init__.py
doctr/models/classification/predictor/pytorch.py
doctr/models/classification/resnet/__init__.py
doctr/models/classification/resnet/pytorch.py
doctr/models/classification/textnet/__init__.py
doctr/models/classification/textnet/pytorch.py
doctr/models/classification/vgg/__init__.py
doctr/models/classification/vgg/pytorch.py
doctr/models/classification/vip/__init__.py
doctr/models/classification/vip/pytorch.py
doctr/models/classification/vip/layers/__init__.py
python_doctr-1.0.0.dist-info/licenses/LICENSE
python_doctr-1.0.0.dist-info/METADATA
python_doctr-1.0.0.dist-info/WHEEL
python_doctr-1.0.0.dist-info/top_level.txt
python_doctr-1.0.0.dist-info/zip-safe
python_doctr-1.0.0.dist-info/RECORD
